extracter/__init__.py
extracter/ig/__init__.py
extracter/ig/information_gain.py
extracter/tfidf/__init__.py
extracter/tfidf/tfidf.py
features_extracter-0.1.1.dist-info/DESCRIPTION.rst
features_extracter-0.1.1.dist-info/METADATA
features_extracter-0.1.1.dist-info/RECORD
features_extracter-0.1.1.dist-info/WHEEL
features_extracter-0.1.1.dist-info/metadata.json
features_extracter-0.1.1.dist-info/top_level.txt
